dsllm/__init__.py
dsllm/core.py
dsllm/exceptions.py
dsllm/types.py
dsllm/generators/__init__.py
dsllm/generators/sql/__init__.py
dsllm/generators/sql/generator.py
dsllm/generators/sql/postflight.py
dsllm/generators/sql/prompt.py
dsllm/generators/sql/validation.py
dsllm/providers/__init__.py
dsllm/providers/openai/__init__.py
dsllm/providers/openai/provider.py
dsllm-0.1.0.dist-info/licenses/LICENSE
dsllm-0.1.0.dist-info/METADATA
dsllm-0.1.0.dist-info/WHEEL
dsllm-0.1.0.dist-info/top_level.txt
dsllm-0.1.0.dist-info/RECORD
